{"name":"Qt-bubble-shooter-","tagline":"The bubble shooter game with 3 difficulty modes. Developed in Qt Creator ","body":"# Qt-Bubble-Shooter-\r\nThe bubble shooter game with 3 difficulty modes. Developed in Qt Creator \r\n\r\nPlaying Modes:\r\n\tNovice- you are allowed to miss (not connect 3 or more same coloured bubbles) 5 times before a new line is added.\r\n\tExpert- you are allowed to miss 3 times before a new line is added.\r\n\tMaster- you are allowed to miss 3 times before a new line is added. However, you only have 5 seconds to take your turn. If the 5 seconds are up, your bubble is automatically shot.\r\n\r\nNotes:\r\n\tYou can click help to learn how to play the game.\r\n\tA text file will be created to keep track of the top ten high scores. This file will open at the beginning of every game. You can also open it by clicking the button.","google":"","note":"Don't delete this file! It's used internally to help with page regeneration."}